<annotation>
	<folder>Deep</folder>
	<filename>bangkok-thailand-october-13-2016-260nw-497856574.jpg</filename>
	<path>D:\Deeick\Drone-Detection-System\Deep\bangkok-thailand-october-13-2016-260nw-497856574.jpg</path>
	<source>
		<database>Unknown</database>
	</source>
	<size>
		<width>390</width>
		<height>280</height>
		<depth>3</depth>
	</size>
	<segmented>0</segmented>
	<object>
		<name>drone</name>
		<pose>Unspecified</pose>
		<truncated>0</truncated>
		<difficult>0</difficult>
		<bndbox>
			<xmin>94</xmin>
			<ymin>101</ymin>
			<xmax>157</xmax>
			<ymax>141</ymax>
		</bndbox>
	</object>
</annotation>
